pyllm_utils/__init__.py
pyllm_utils/agent.py
pyllm_utils/agent_utils/__init__.py
pyllm_utils/agent_utils/agent_message.py
pyllm_utils/anthropic_api/__init__.py
pyllm_utils/anthropic_api/anthropic_chat_history_manager.py
pyllm_utils/anthropic_api/anthropic_client.py
pyllm_utils/anthropic_api/anthropic_message_converter.py
pyllm_utils/base_api/base_message_converter.py
pyllm_utils/common_converter/__init__.py
pyllm_utils/common_converter/data_encoder.py
pyllm_utils/common_converter/json_converter.py
pyllm_utils/common_converter/json_stream_converter.py
pyllm_utils/gemini_api/__init__.py
pyllm_utils/gemini_api/gemini_chat_history_manager.py
pyllm_utils/gemini_api/gemini_client.py
pyllm_utils/gemini_api/gemini_message_converter.py
pyllm_utils/llama_cpp_api/__init__.py
pyllm_utils/llama_cpp_api/llama_cpp_chat_history_manager-shoichi.py
pyllm_utils/llama_cpp_api/llama_cpp_chat_history_manager.py
pyllm_utils/llama_cpp_api/llama_cpp_client.py
pyllm_utils/llama_cpp_api/llama_cpp_message_converter.py
pyllm_utils/llm.py
pyllm_utils/models/local_models.json
pyllm_utils/models/models.json
pyllm_utils/openai_api/__init__.py
pyllm_utils/openai_api/openai_chat_history_manager.py
pyllm_utils/openai_api/openai_client.py
pyllm_utils/openai_api/openai_message_converter.py
pyllm_utils/test_utils/test_llm.py
pyllm_utils/tests/__init__.py
pyllm_utils/tests/conftest.py
pyllm_utils/tests/test_anthropic_client.py
pyllm_utils/tests/test_datas/test.mp3
pyllm_utils/tests/test_datas/test.png
pyllm_utils/tests/test_gemini_client.py
pyllm_utils/tests/test_gui_controller.py
pyllm_utils/tests/test_img_pos_getter.py
pyllm_utils/tests/test_ipython_controller.py
pyllm_utils/tests/test_llama_cpp_client.py
pyllm_utils/tests/test_llm.py
pyllm_utils/tests/test_openai_client.py
pyllm_utils/tests/test_outputs/latest_screenshot.jpg
pyllm_utils/tests/test_outputs/latest_screenshot_with_bbox.jpg
pyllm_utils/tests/test_outputs/latest_screenshot_with_point.jpg
pyllm_utils/tests/test_outputs/output.wav
pyllm_utils-0.1.26.dist-info/METADATA
pyllm_utils-0.1.26.dist-info/WHEEL
pyllm_utils-0.1.26.dist-info/RECORD
