Metadata-Version: 2.1
Name: pyllm_utils
Version: 0.1.26
Summary: 
Author: shokitano0521
Author-email: s.kitano.h050521@gmail.com
Requires-Python: >=3.12,<4.0
Classifier: Programming Language :: Python :: 3
Classifier: Programming Language :: Python :: 3.12
Classifier: Programming Language :: Python :: 3.13
Requires-Dist: anthropic (>=0.42.0,<0.43.0)
Requires-Dist: clickhouse-driver (>=0.2.9,<0.3.0)
Requires-Dist: google-generativeai (>=0.8.3,<0.9.0)
Requires-Dist: ipython (>=8.31.0,<9.0.0)
Requires-Dist: mss (>=10.0.0,<11.0.0)
Requires-Dist: numpy (>=2.2.1,<3.0.0)
Requires-Dist: openai (>=1.58.1,<2.0.0)
Requires-Dist: pillow (>=11.0.0,<12.0.0)
Requires-Dist: pyautogui (>=0.9.54,<0.10.0)
Requires-Dist: pymilvus (>=2.5.1,<3.0.0)
Requires-Dist: pyvirtualdisplay (>=3.0,<4.0)
Requires-Dist: tiktoken (>=0.8.0,<0.9.0)
Requires-Dist: voyageai (>=0.3.2,<0.4.0) ; python_version < "3.13"
